simianpy/__init__.py
simianpy/_version.py
simianpy/analysis/ROC.py
simianpy/analysis/__init__.py
simianpy/analysis/behaviouraldata.py
simianpy/analysis/blink_mask.py
simianpy/analysis/csd.py
simianpy/analysis/spectrogram.py
simianpy/analysis/spikedensity.py
simianpy/analysis/gaze/__init__.py
simianpy/analysis/gaze/gazedata.py
simianpy/analysis/lfp/__init__.py
simianpy/analysis/lfp/compute_csd.py
simianpy/analysis/lfp/multitaper_lfp_power.py
simianpy/analysis/lfp/phase.py
simianpy/analysis/spiketrain/__init__.py
simianpy/analysis/spiketrain/spiketrainset.py
simianpy/analysis/spiketrain/spiketrainsetviewer.py
simianpy/analysis/spiketrain/bursting/__init__.py
simianpy/analysis/spiketrain/bursting/poisson_burst_detection.py
simianpy/analysis/spiketrain/ccg/__init__.py
simianpy/analysis/spiketrain/ccg/ccg.py
simianpy/analysis/spiketrain/ccg/ccg_overall.py
simianpy/analysis/spiketrain/jpsth/__init__.py
simianpy/analysis/spiketrain/jpsth/compute_coincidence_histogram.py
simianpy/analysis/spiketrain/jpsth/compute_covariogram.py
simianpy/analysis/spiketrain/jpsth/compute_crosscorr.py
simianpy/analysis/spiketrain/jpsth/compute_psth_stats.py
simianpy/analysis/spiketrain/jpsth/find_longest_significant_span.py
simianpy/analysis/spiketrain/jpsth/jpsth.py
simianpy/analysis/spiketrain/jpsth/normalize_jpsth.py
simianpy/analysis/stats/__init__.py
simianpy/analysis/stats/circular.py
simianpy/analysis/stats/linear_regression.py
simianpy/analysis/stats/pearsonr_many.py
simianpy/analysis/stats/xarray/__init__.py
simianpy/analysis/stats/xarray/cpd.py
simianpy/analysis/stats/xarray/ttest_ind.py
simianpy/analysis/stats/xarray/ttest_rel.py
simianpy/io/File.py
simianpy/io/__init__.py
simianpy/io/convert.py
simianpy/io/intan/__init__.py
simianpy/io/intan/io.py
simianpy/io/intan/load_intan_rhs_format.py
simianpy/io/intan/intanutil/__init__.py
simianpy/io/intan/intanutil/data_to_result.py
simianpy/io/intan/intanutil/get_bytes_per_data_block.py
simianpy/io/intan/intanutil/notch_filter.py
simianpy-0.1.16.dist-info/METADATA
simianpy-0.1.16.dist-info/WHEEL
simianpy-0.1.16.dist-info/entry_points.txt
simianpy-0.1.16.dist-info/licenses/LICENSE.txt
simianpy-0.1.16.dist-info/RECORD
