Metadata-Version: 2.4
Name: simianpy
Version: 0.1.16
Summary: Data analysis tools designed for working with primate neuroscientific data
Author-email: Janahan Selvanayagam <me@janahan.ca>
License-File: LICENSE.txt
Keywords: behaviour,electrophysiology,signal processing
Requires-Python: >=3.13
Requires-Dist: click
Requires-Dist: h5py
Requires-Dist: matplotlib
Requires-Dist: numpy
Requires-Dist: pandas
Requires-Dist: pyyaml
Requires-Dist: scipy
Requires-Dist: tables
Requires-Dist: tqdm
Requires-Dist: xarray
Provides-Extra: full
Requires-Dist: colorama; extra == 'full'
Requires-Dist: dask[array]; extra == 'full'
Requires-Dist: ipython; extra == 'full'
Requires-Dist: pyqtmgl; extra == 'full'
Requires-Dist: ssqueezepy>=0.6.6; extra == 'full'
